de_client/__init__.py
de_client-0.0.1.dist-info/LICENSE
de_client-0.0.1.dist-info/METADATA
de_client-0.0.1.dist-info/WHEEL
de_client-0.0.1.dist-info/top_level.txt
de_client-0.0.1.dist-info/RECORD
