Metadata-Version: 2.1
Name: de-client
Version: 0.0.1
Summary: A Public stub for de-client by Plotly
Home-page: https://plotly.com/dash/
Author: Alex Johnson
Author-email: alex@plotly.com
License: Commercial
Classifier: Programming Language :: Python :: 3
Classifier: Framework :: Dash
License-File: LICENSE
